MANIFEST.in
Makefile.am
README.rst
ast.cpp
ast.hpp
ast_def_macros.hpp
ast_factory.hpp
ast_fwd_decl.hpp
backtrace.hpp
base64vlq.cpp
base64vlq.hpp
bind.cpp
bind.hpp
color_names.hpp
constants.cpp
constants.hpp
context.cpp
context.hpp
contextualize.cpp
contextualize.hpp
copy_c_str.cpp
copy_c_str.hpp
emscripten_wrapper.cpp
emscripten_wrapper.hpp
environment.hpp
error_handling.cpp
error_handling.hpp
eval.cpp
eval.hpp
expand.cpp
expand.hpp
extend.cpp
extend.hpp
file.cpp
file.hpp
functions.cpp
functions.hpp
inspect.cpp
inspect.hpp
kwd_arg_macros.hpp
mapping.hpp
memory_manager.hpp
operation.hpp
output_compressed.cpp
output_compressed.hpp
output_nested.cpp
output_nested.hpp
parser.cpp
parser.hpp
paths.hpp
position.hpp
prelexer.cpp
prelexer.hpp
pysass.c
sass.cpp
sass.h
sass.py
sass_interface.cpp
sass_interface.h
sassc.py
sasstests.py
setup.cfg
setup.py
source_map.cpp
source_map.hpp
subset_map.hpp
to_c.cpp
to_c.hpp
to_string.cpp
to_string.hpp
token.hpp
trim.cpp
trim.hpp
units.cpp
units.hpp
libsass_unstable.egg-info/PKG-INFO
libsass_unstable.egg-info/SOURCES.txt
libsass_unstable.egg-info/dependency_links.txt
libsass_unstable.egg-info/entry_points.txt
libsass_unstable.egg-info/requires.txt
libsass_unstable.egg-info/top_level.txt
sass2scss/sass2scss.cpp
sass2scss/sass2scss.h
sassutils/__init__.py
sassutils/builder.py
sassutils/distutils.py
sassutils/wsgi.py
test/a.scss
test/b.scss
test/c.scss
test/d.scss
win32/unistd.h