Metadata-Version: 1.1
Name: libsass-unstable
Version: 0.4.2-20140528-cd3ee1cbe3
Summary: SASS for Python: A straightforward binding of libsass for Python.
Home-page: http://dahlia.kr/libsass-python/
Author: Hong Minhee
Author-email: minhee@dahlia.kr
License: MIT License
Download-URL: https://github.com/dahlia/libsass-python/releases
Platform: UNKNOWN
Classifier: Development Status :: 5 - Production/Stable
Classifier: Environment :: Web Environment
Classifier: Intended Audience :: Developers
Classifier: License :: OSI Approved :: MIT License
Classifier: Operating System :: OS Independent
Classifier: Programming Language :: C
Classifier: Programming Language :: C++
Classifier: Programming Language :: Python :: 2.6
Classifier: Programming Language :: Python :: 2.7
Classifier: Programming Language :: Python :: 3
Classifier: Programming Language :: Python :: 3.3
Classifier: Programming Language :: Python :: 3.4
Classifier: Topic :: Internet :: WWW/HTTP
Classifier: Topic :: Internet :: WWW/HTTP :: Dynamic Content
Classifier: Topic :: Software Development :: Code Generators
Classifier: Topic :: Software Development :: Compilers
